my_wanglei/__init__.py
my_wanglei-0.1.0.dist-info/METADATA
my_wanglei-0.1.0.dist-info/WHEEL
my_wanglei-0.1.0.dist-info/top_level.txt
my_wanglei-0.1.0.dist-info/RECORD
